[{"date":"2025/09/01","wind":"亂流"},{"date":"2025/09/02","wind":"亂流"},{"date":"2025/09/03","wind":"亂流"},{"date":"2025/09/04","wind":"亂流"},{"date":"2025/09/05","wind":"強風"},{"date":"2025/09/08","wind":"強風"},{"date":"2025/09/09","wind":"強風"},{"date":"2025/09/10","wind":"強風"},{"date":"2025/09/11","wind":"亂流"},{"date":"2025/09/12","wind":"亂流"},{"date":"2025/09/15","wind":"亂流"},{"date":"2025/09/16","wind":"亂流"},{"date":"2025/09/17","wind":"亂流"},{"date":"2025/09/18","wind":"強風"},{"date":"2025/09/19","wind":"強風"},{"date":"2025/09/22","wind":"強風"},{"date":"2025/09/23","wind":"強風"},{"date":"2025/09/24","wind":"亂流"},{"date":"2025/09/25","wind":"亂流"},{"date":"2025/09/26","wind":"無風"},{"date":"2025/09/30","wind":"亂流"},{"date":"2025/10/01","wind":"亂流"},{"date":"2025/10/02","wind":"強風"},{"date":"2025/10/03","wind":"強風"},{"date":"2025/10/07","wind":"強風"},{"date":"2025/10/08","wind":"強風"},{"date":"2025/10/09","wind":"強風"},{"date":"2025/10/13","wind":"無風"},{"date":"2025/10/14","wind":"無風"},{"date":"2025/10/15","wind":"無風"},{"date":"2025/10/16","wind":"強風"},{"date":"2025/10/17","wind":"陣風"},{"date":"2025/10/20","wind":"強風"},{"date":"2025/10/21","wind":"強風"},{"date":"2025/10/22","wind":"強風"},{"date":"2025/10/23","wind":"亂流"},{"date":"2025/10/27","wind":"強風"},{"date":"2025/10/28","wind":"強風"},{"date":"2025/10/29","wind":"強風"},{"date":"2025/10/30","wind":"無風"},{"date":"2025/10/31","wind":"強風"},{"date":"2025/11/03","wind":"強風"},{"date":"2025/11/04","wind":"無風"},{"date":"2025/11/05","wind":"無風"},{"date":"2025/11/06","wind":"陣風"},{"date":"2025/11/07","wind":"無風"},{"date":"2025/11/10","wind":"無風"},{"date":"2025/11/11","wind":"無風"},{"date":"2025/11/12","wind":"陣風"},{"date":"2025/11/13","wind":"陣風"},{"date":"2025/11/14","wind":"無風"},{"date":"2025/11/17","wind":"無風"},{"date":"2025/11/18","wind":"無風"},{"date":"2025/11/19","wind":"無風"},{"date":"2025/11/20","wind":"陣風"},{"date":"2025/11/21","wind":"無風"},{"date":"2025/11/24","wind":"陣風"},{"date":"2025/11/25","wind":"陣風"},{"date":"2025/11/26","wind":"陣風"},{"date":"2025/11/27","wind":"強風"},{"date":"2025/11/28","wind":"強風"},{"date":"2025/12/01","wind":"強風"},{"date":"2025/12/02","wind":"強風"},{"date":"2025/12/03","wind":"強風"},{"date":"2025/12/04","wind":"亂流"},{"date":"2025/12/05","wind":"亂流"},{"date":"2025/12/08","wind":"強風"},{"date":"2025/12/09","wind":"強風"},{"date":"2025/12/10","wind":"強風"},{"date":"2025/12/11","wind":"亂流"},{"date":"2025/12/12","wind":"亂流"},{"date":"2025/12/15","wind":"亂流"},{"date":"2025/12/16","wind":"亂流"},{"date":"2025/12/17","wind":"亂流"},{"date":"2025/12/18","wind":"無風"},{"date":"2025/12/19","wind":"亂流"},{"date":"2025/12/22","wind":"強風"},{"date":"2025/12/23","wind":"強風"},{"date":"2025/12/24","wind":"強風"},{"date":"2025/12/26","wind":"強風"},{"date":"2025/12/29","wind":"強風"},{"date":"2025/12/30","wind":"強風"},{"date":"2025/12/31","wind":"強風"},{"date":"2026/01/02","wind":"強風"},{"date":"2026/01/05","wind":"亂流"},{"date":"2026/01/06","wind":"亂流"},{"date":"2026/01/07","wind":"強風"},{"date":"2026/01/08","wind":"亂流"},{"date":"2026/01/09","wind":"亂流"},{"date":"2026/01/12","wind":"強風"},{"date":"2026/01/13","wind":"強風"},{"date":"2026/01/14","wind":"強風"},{"date":"2026/01/15","wind":"強風"},{"date":"2026/01/16","wind":"強風"},{"date":"2026/01/19","wind":"強風"},{"date":"2026/01/20","wind":"強風"},{"date":"2026/01/21","wind":"亂流"},{"date":"2026/01/22","wind":"亂流"},{"date":"2026/01/23","wind":"亂流"},{"date":"2026/01/26","wind":"強風"},{"date":"2026/01/27","wind":"強風"},{"date":"2026/01/28","wind":"強風"},{"date":"2026/01/29","wind":"亂流"},{"date":"2026/01/30","wind":"亂流"},{"date":"2026/02/02","wind":"亂流"},{"date":"2026/02/03","wind":"亂流"},{"date":"2026/02/04","wind":"亂流"},{"date":"2026/02/05","wind":"亂流"},{"date":"2026/02/06","wind":"無風"},{"date":"2026/02/09","wind":"陣風"},{"date":"2026/02/10","wind":"陣風"},{"date":"2026/02/11","wind":"陣風"},{"date":"2026/02/23","wind":"強風"},{"date":"2026/02/24","wind":"強風"},{"date":"2026/02/25","wind":"強風"},{"date":"2026/02/26","wind":"強風"},{"date":"2026/03/02","wind":"強風"},{"date":"2026/03/03","wind":"亂流"},{"date":"2026/03/04","wind":"無風"},{"date":"2026/03/05","wind":"亂流"},{"date":"2026/03/06","wind":"亂流"},{"date":"2026/03/09","wind":"無風"},{"date":"2026/03/10","wind":"無風"},{"date":"2026/03/11","wind":"強風"},{"date":"2026/03/12","wind":"強風"},{"date":"2026/03/13","wind":"強風"},{"date":"2026/03/16","wind":"強風"},{"date":"2026/03/17","wind":"強風"},{"date":"2026/03/18","wind":"強風"},{"date":"2026/03/19","wind":"強風"},{"date":"2026/03/20","wind":"強風"},{"date":"2026/03/23","wind":"亂流"},{"date":"2026/03/24","wind":"亂流"},{"date":"2026/03/25","wind":"亂流"},{"date":"2026/03/26","wind":"亂流"},{"date":"2026/03/27","wind":"亂流"},{"date":"2026/03/30","wind":"亂流"},{"date":"2026/03/31","wind":"無風"},{"date":"2026/04/01","wind":"亂流"},{"date":"2026/04/02","wind":"強風"},{"date":"2026/04/07","wind":"強風"},{"date":"2026/04/08","wind":"強風"},{"date":"2026/04/09","wind":"強風"},{"date":"2026/04/10","wind":"強風"},{"date":"2026/04/13","wind":"強風"},{"date":"2026/04/14","wind":"強風"},{"date":"2026/04/15","wind":"強風"},{"date":"2026/04/16","wind":"強風"},{"date":"2026/04/17","wind":"強風"},{"date":"2026/04/20","wind":"強風"},{"date":"2026/04/21","wind":"強風"},{"date":"2026/04/22","wind":"強風"},{"date":"2026/04/23","wind":"亂流"},{"date":"2026/04/24","wind":"亂流"},{"date":"2026/04/27","wind":"亂流"},{"date":"2026/04/28","wind":"亂流"},{"date":"2026/04/29","wind":"亂流"},{"date":"2026/04/30","wind":"亂流"},{"date":"2026/05/04","wind":"強風"},{"date":"2026/05/05","wind":"強風"},{"date":"2026/05/06","wind":"強風"},{"date":"2026/05/07","wind":"強風"},{"date":"2026/05/08","wind":"亂流"},{"date":"2026/05/11","wind":"強風"},{"date":"2026/05/12","wind":"強風"},{"date":"2026/05/13","wind":"亂流"},{"date":"2026/05/14","wind":"亂流"},{"date":"2026/05/15","wind":"亂流"},{"date":"2026/05/18","wind":"亂流"},{"date":"2026/05/19","wind":"無風"},{"date":"2026/05/20","wind":"無風"},{"date":"2026/05/21","wind":"強風"},{"date":"2026/05/22","wind":"強風"},{"date":"2026/05/25","wind":"強風"},{"date":"2026/05/26","wind":"強風"},{"date":"2026/05/27","wind":"強風"},{"date":"2026/05/28","wind":"亂流"},{"date":"2026/05/29","wind":"強風"},{"date":"2026/06/01","wind":"強風"},{"date":"2026/06/02","wind":"亂流"},{"date":"2026/06/03","wind":"亂流"},{"date":"2026/06/04","wind":"亂流"},{"date":"2026/06/05","wind":"亂流"},{"date":"2026/06/08","wind":"強風"}]